tests
vaquero
